ni/measurementlink/pinmap/v1/client/__init__.py
ni/measurementlink/pinmap/v1/client/_client.py
ni/measurementlink/pinmap/v1/client/_client_base.py
ni/measurementlink/pinmap/v1/client/py.typed
ni_measurementlink_pinmap_v1_client-1.1.0.dist-info/METADATA
ni_measurementlink_pinmap_v1_client-1.1.0.dist-info/WHEEL
ni_measurementlink_pinmap_v1_client-1.1.0.dist-info/RECORD
