Metadata-Version: 2.3
Name: ni.measurementlink.pinmap.v1.client
Version: 1.1.0
Summary: gRPC Client for NI Pin Map Service
License: MIT
Keywords: pinmap,client
Author: NI
Author-email: opensource@ni.com
Maintainer: Joe Friedrichsen
Maintainer-email: joe.friedrichsen@emerson.com
Requires-Python: >=3.10,<4.0
Classifier: Development Status :: 5 - Production/Stable
Classifier: Intended Audience :: Developers
Classifier: Intended Audience :: Manufacturing
Classifier: Intended Audience :: Science/Research
Classifier: License :: OSI Approved :: MIT License
Classifier: Operating System :: Microsoft :: Windows
Classifier: Operating System :: POSIX
Classifier: Programming Language :: Python :: 3
Classifier: Programming Language :: Python :: 3.10
Classifier: Programming Language :: Python :: 3.11
Classifier: Programming Language :: Python :: 3.12
Classifier: Programming Language :: Python :: 3.13
Classifier: Programming Language :: Python :: 3.14
Classifier: Programming Language :: Python :: Implementation :: CPython
Requires-Dist: grpcio (>=1.49.0,<2.0)
Requires-Dist: ni-grpc-extensions (>=1.1.0)
Requires-Dist: ni-measurementlink-discovery-v1-client (>=1.1.0)
Requires-Dist: ni-measurementlink-measurement-v1-proto (>=1.1.1)
Requires-Dist: ni-measurementlink-measurement-v2-proto (>=1.1.1)
Requires-Dist: ni-measurementlink-pinmap-v1-proto (>=1.1.0)
Requires-Dist: ni-measurementlink-sessionmanagement-v1-client (>=1.1.0)
Project-URL: Documentation, https://nimeasurementlinkpinmapv1client.readthedocs.io/en/latest/
Project-URL: Repository, https://github.com/ni/ni-apis-python
